mkdocs_xrepos_plugin/__init__.py
mkdocs_xrepos_plugin/plugin.py
mkdocs_xrepos_plugin/scripts/mv_docs_up.sh
mkdocs_xrepos_plugin/scripts/sparse_clone.sh
mkdocs_xrepos_plugin/scripts/sparse_clone_old.sh
mkdocs_xrepos_plugin/structure.py
mkdocs_xrepos_plugin/util.py
mkdocs_xrepos_plugin-1.0.dist-info/METADATA
mkdocs_xrepos_plugin-1.0.dist-info/WHEEL
mkdocs_xrepos_plugin-1.0.dist-info/entry_points.txt
mkdocs_xrepos_plugin-1.0.dist-info/RECORD
